Metadata-Version: 1.1
Name: covid19icu
Version: 0.0.2
Summary: A tool for the estimation of ICU beds occupied by COVID-19 patients
Home-page: https://github.com/aresio/COVID-19-ICU
Author: Marco S. Nobile
Author-email: m.s.nobile@tue.nl
License: LICENSE.txt
Keywords: modeling,fuzzy self-tuning particle swarm optimization,predictive models,intensive care,covid-19
Platform: UNKNOWN
Classifier: Programming Language :: Python :: 3.7
